<?xml version="1.0" encoding="UTF-8"?>
<mule xmlns:api-gateway="http://www.mulesoft.org/schema/mule/api-gateway"
	xmlns:ee="http://www.mulesoft.org/schema/mule/ee/core" xmlns:salesforce="http://www.mulesoft.org/schema/mule/salesforce" xmlns:doc="http://www.mulesoft.org/schema/mule/documentation" xmlns="http://www.mulesoft.org/schema/mule/core" xmlns:apikit="http://www.mulesoft.org/schema/mule/mule-apikit" xmlns:http="http://www.mulesoft.org/schema/mule/http" xmlns:xsi="http://www.w3.org/2001/XMLSchema-instance" xsi:schemaLocation="http://www.mulesoft.org/schema/mule/core http://www.mulesoft.org/schema/mule/core/current/mule.xsd http://www.mulesoft.org/schema/mule/http http://www.mulesoft.org/schema/mule/http/current/mule-http.xsd http://www.mulesoft.org/schema/mule/mule-apikit http://www.mulesoft.org/schema/mule/mule-apikit/current/mule-apikit.xsd 
http://www.mulesoft.org/schema/mule/salesforce http://www.mulesoft.org/schema/mule/salesforce/current/mule-salesforce.xsd
http://www.mulesoft.org/schema/mule/api-gateway http://www.mulesoft.org/schema/mule/api-gateway/current/mule-api-gateway.xsd">
    <http:listener-config name="salesforce-crud-design-api-httpListenerConfig">
        <http:listener-connection host="0.0.0.0" port="8082" />
    </http:listener-config>
    <apikit:config name="salesforce-crud-design-api-config" api="salesforce-crud-design-api.raml" outboundHeadersMapName="outboundHeaders" httpStatusVarName="httpStatus" />
    <salesforce:sfdc-config name="Salesforce_Config" doc:name="Salesforce Config" doc:id="d8d76d71-a78a-4fa9-a502-f45a5c6d3251" >
		<salesforce:cached-basic-connection username="manjunathmails1@gmail.com" password="Bhavesh001" securityToken="HeHs0ZJRS2ntsWWCuTjtA1sM" />
	</salesforce:sfdc-config>
	<api-gateway:autodiscovery apiId="15886646" doc:name="API Autodiscovery" doc:id="a558364c-c885-42b1-9e9a-2eb5c86cffd5" flowRef="salesforce-crud-design-api-main" />
	<flow name="salesforce-crud-design-api-main">
        <http:listener config-ref="salesforce-crud-design-api-httpListenerConfig" path="/salesforce/*">
            <http:response statusCode="#[vars.httpStatus default 200]">
                <http:headers><![CDATA[#[vars.outboundHeaders default {}]]]></http:headers>
            </http:response>
            <http:error-response statusCode="#[vars.httpStatus default 500]">
                <http:body><![CDATA[#[payload]]]></http:body>
                <http:headers><![CDATA[#[vars.outboundHeaders default {}]]]></http:headers>
            </http:error-response>
        </http:listener>
        <apikit:router config-ref="salesforce-crud-design-api-config" />
        <error-handler>
            <on-error-propagate type="APIKIT:BAD_REQUEST">
                <ee:transform xmlns:ee="http://www.mulesoft.org/schema/mule/ee/core" xsi:schemaLocation="http://www.mulesoft.org/schema/mule/ee/core http://www.mulesoft.org/schema/mule/ee/core/current/mule-ee.xsd">
                    <ee:message>
                        <ee:set-payload><![CDATA[%dw 2.0
output application/json
---
{message: "Bad request"}]]></ee:set-payload>
                    </ee:message>
                    <ee:variables>
                        <ee:set-variable variableName="httpStatus">400</ee:set-variable>
                    </ee:variables>
                </ee:transform>
            </on-error-propagate>
            <on-error-propagate type="APIKIT:NOT_FOUND">
                <ee:transform xmlns:ee="http://www.mulesoft.org/schema/mule/ee/core" xsi:schemaLocation="http://www.mulesoft.org/schema/mule/ee/core http://www.mulesoft.org/schema/mule/ee/core/current/mule-ee.xsd">
                    <ee:message>
                        <ee:set-payload><![CDATA[%dw 2.0
output application/json
---
{message: "Resource not found"}]]></ee:set-payload>
                    </ee:message>
                    <ee:variables>
                        <ee:set-variable variableName="httpStatus">404</ee:set-variable>
                    </ee:variables>
                </ee:transform>
            </on-error-propagate>
            <on-error-propagate type="APIKIT:METHOD_NOT_ALLOWED">
                <ee:transform xmlns:ee="http://www.mulesoft.org/schema/mule/ee/core" xsi:schemaLocation="http://www.mulesoft.org/schema/mule/ee/core http://www.mulesoft.org/schema/mule/ee/core/current/mule-ee.xsd">
                    <ee:message>
                        <ee:set-payload><![CDATA[%dw 2.0
output application/json
---
{message: "Method not allowed"}]]></ee:set-payload>
                    </ee:message>
                    <ee:variables>
                        <ee:set-variable variableName="httpStatus">405</ee:set-variable>
                    </ee:variables>
                </ee:transform>
            </on-error-propagate>
            <on-error-propagate type="APIKIT:NOT_ACCEPTABLE">
                <ee:transform xmlns:ee="http://www.mulesoft.org/schema/mule/ee/core" xsi:schemaLocation="http://www.mulesoft.org/schema/mule/ee/core http://www.mulesoft.org/schema/mule/ee/core/current/mule-ee.xsd">
                    <ee:message>
                        <ee:set-payload><![CDATA[%dw 2.0
output application/json
---
{message: "Not acceptable"}]]></ee:set-payload>
                    </ee:message>
                    <ee:variables>
                        <ee:set-variable variableName="httpStatus">406</ee:set-variable>
                    </ee:variables>
                </ee:transform>
            </on-error-propagate>
            <on-error-propagate type="APIKIT:UNSUPPORTED_MEDIA_TYPE">
                <ee:transform xmlns:ee="http://www.mulesoft.org/schema/mule/ee/core" xsi:schemaLocation="http://www.mulesoft.org/schema/mule/ee/core http://www.mulesoft.org/schema/mule/ee/core/current/mule-ee.xsd">
                    <ee:message>
                        <ee:set-payload><![CDATA[%dw 2.0
output application/json
---
{message: "Unsupported media type"}]]></ee:set-payload>
                    </ee:message>
                    <ee:variables>
                        <ee:set-variable variableName="httpStatus">415</ee:set-variable>
                    </ee:variables>
                </ee:transform>
            </on-error-propagate>
            <on-error-propagate type="APIKIT:NOT_IMPLEMENTED">
                <ee:transform xmlns:ee="http://www.mulesoft.org/schema/mule/ee/core" xsi:schemaLocation="http://www.mulesoft.org/schema/mule/ee/core http://www.mulesoft.org/schema/mule/ee/core/current/mule-ee.xsd">
                    <ee:message>
                        <ee:set-payload><![CDATA[%dw 2.0
output application/json
---
{message: "Not Implemented"}]]></ee:set-payload>
                    </ee:message>
                    <ee:variables>
                        <ee:set-variable variableName="httpStatus">501</ee:set-variable>
                    </ee:variables>
                </ee:transform>
            </on-error-propagate>
        </error-handler>
    </flow>
    <flow name="salesforce-crud-design-api-console">
        <http:listener config-ref="salesforce-crud-design-api-httpListenerConfig" path="/console/*">
            <http:response statusCode="#[vars.httpStatus default 200]">
                <http:headers>#[vars.outboundHeaders default {}]</http:headers>
            </http:response>
            <http:error-response statusCode="#[vars.httpStatus default 500]">
                <http:body>#[payload]</http:body>
                <http:headers>#[vars.outboundHeaders default {}]</http:headers>
            </http:error-response>
        </http:listener>
        <apikit:console config-ref="salesforce-crud-design-api-config" />
        <error-handler>
            <on-error-propagate type="APIKIT:NOT_FOUND">
                <ee:transform xmlns:ee="http://www.mulesoft.org/schema/mule/ee/core" xsi:schemaLocation="http://www.mulesoft.org/schema/mule/ee/core http://www.mulesoft.org/schema/mule/ee/core/current/mule-ee.xsd">
                    <ee:message>
                        <ee:set-payload><![CDATA[%dw 2.0
output application/json
---
{message: "Resource not found"}]]></ee:set-payload>
                    </ee:message>
                    <ee:variables>
                        <ee:set-variable variableName="httpStatus">404</ee:set-variable>
                    </ee:variables>
                </ee:transform>
            </on-error-propagate>
        </error-handler>
    </flow>
    <flow name="get:\fetchAccounts:salesforce-crud-design-api-config">
        <flow-ref doc:name="Flow Reference" doc:id="727472d5-376c-4376-997a-826c82f081f9" name="fetchAccountsFlow"/>
    </flow>
    <flow name="get:\fetchAccountsWithBillingCity:salesforce-crud-design-api-config">
        <logger level="INFO" doc:name="Logger" doc:id="1ea184e0-b920-440e-a3d2-180371851d96" message="In the entry of the logger in the param with BillingCity #[attributes.queryParams.billingCity]"/>
		<set-variable value="#[attributes.queryParams.billingCity default '']" doc:name="Set Variable" doc:id="afab15a3-ec08-4a8a-ae0d-45d21ecb7052" variableName="billingCityVar"/>
		<flow-ref doc:name="Flow Reference" doc:id="9cc41f13-0c82-4bf9-8831-7492cda8418c" name="fetchAccountsWithBillingCityFlow"/>
		<logger level="INFO" doc:name="Logger" doc:id="caf7c01a-f619-4c9e-8b0c-1c3adb318c34" message="Tranformation completed #[payload]"/>
    </flow>
</mule>
